{
  "id": "analyzer",
  "name": "Analyzer",
  "version": "0.1.0",
  "description": "YouTube video effect analysis — detect edits, transitions, and effects from reference videos",
  "author": "Trevor May",
  "main": "src/index.ts",
  "repository": "IamTrevorMay/mayday-analyzer",
  "minSdkVersion": "2.0.0",
  "hasCep": false,
  "permissions": ["ai", "media"],
  "ui": {
    "page": true,
    "sidebarLabel": "Analyzer",
    "sidebarOrder": 50
  },
  "marketplace": {
    "category": "analysis",
    "tags": ["youtube", "effects", "training", "reference"]
  },
  "targetApp": "premiere"
}
